wherehouse/__init__.py
wherehouse/centroid/__init__.py
wherehouse/centroid/network_utils.py
wherehouse/centroid/models/__init__.py
wherehouse/centroid/models/raster.py
wherehouse-0.1.3.dist-info/DESCRIPTION.rst
wherehouse-0.1.3.dist-info/LICENSE.txt
wherehouse-0.1.3.dist-info/METADATA
wherehouse-0.1.3.dist-info/RECORD
wherehouse-0.1.3.dist-info/WHEEL
wherehouse-0.1.3.dist-info/metadata.json
wherehouse-0.1.3.dist-info/top_level.txt
