Metadata-Version: 2.0
Name: wherehouse
Version: 0.1.3
Summary: A Python client for Wherehouse modules
Home-page: https://github.com/wherehouse/wherehouse-sdk-py
Author: Dan Abdinoor
Author-email: dan@wherehou.se
License: MIT
Platform: UNKNOWN
Requires-Dist: pyshp (>=1.2.10)
Provides-Extra: test
Requires-Dist: pytest (>=2.8.3); extra == 'test'
